tests/test_bagua_define.py
tests/__init__.py
tests/internal/compressor.py
tests/internal/multi_process.py
tests/internal/common_utils.py
tests/internal/__init__.py
tests/internal/torch/expecttest.py
tests/internal/torch/common_cuda.py
tests/internal/torch/common_utils.py
tests/internal/torch/_core.py
tests/internal/torch/common_distributed.py
tests/internal/torch/__init__.py
tests/pytorch_lightning/test_bagua_strategy.py
tests/pytorch_lightning/boring_model.py
tests/pytorch_lightning/__init__.py
bagua_core/bagua_install_deps.py
bagua_core/_environment.py
bagua_core/bagua_core.cpython-38-x86_64-linux-gnu.so
bagua_core/__init__.py
bagua_core/.data/bagua-net/libnccl-net.so
bagua_cuda117-0.9.3.dev6.dist-info/top_level.txt
bagua_cuda117-0.9.3.dev6.dist-info/LICENSE
bagua_cuda117-0.9.3.dev6.dist-info/RECORD
bagua_cuda117-0.9.3.dev6.dist-info/METADATA
bagua_cuda117-0.9.3.dev6.dist-info/WHEEL
bagua_cuda117-0.9.3.dev6.dist-info/entry_points.txt
bagua/bagua_define.py
bagua/version.py
bagua/__init__.py
bagua/script/baguarun.py
bagua/script/__init__.py
bagua/service/bayesian_optimizer.py
bagua/service/autotune_task_manager.py
bagua/service/autotune_system.py
bagua/service/autotune_service.py
bagua/service/__init__.py
bagua/distributed/run.py
bagua/distributed/launch.py
bagua/distributed/__init__.py
bagua/torch_api/bucket.py
bagua/torch_api/distributed.py
bagua/torch_api/utils.py
bagua/torch_api/communication.py
bagua/torch_api/env.py
bagua/torch_api/tensor.py
bagua/torch_api/__init__.py
bagua/torch_api/contrib/load_balancing_data_loader.py
bagua/torch_api/contrib/sync_batchnorm.py
bagua/torch_api/contrib/cache_loader.py
bagua/torch_api/contrib/cached_dataset.py
bagua/torch_api/contrib/__init__.py
bagua/torch_api/contrib/utils/redis_store.py
bagua/torch_api/contrib/utils/store.py
bagua/torch_api/contrib/utils/__init__.py
bagua/torch_api/contrib/fuse/optimizer.py
bagua/torch_api/contrib/fuse/__init__.py
bagua/torch_api/model_parallel/__init__.py
bagua/torch_api/model_parallel/moe/experts.py
bagua/torch_api/model_parallel/moe/utils.py
bagua/torch_api/model_parallel/moe/sharded_moe.py
bagua/torch_api/model_parallel/moe/layer.py
bagua/torch_api/model_parallel/moe/__init__.py
